[
    {
        "imageURL": "https://image.yes24.com/goods/128939165/L",
        "title": "2025 이것이 진짜 해설이다 소방설비기사 실기(기계) 최근 11년 기출문제 재분류집",
        "author": "오철호 저",
        "price": "39,600원",
        "url": "/Product/Goods/128939165"
    },
    {
        "imageURL": "https://image.yes24.com/goods/132545589/L",
        "title": "2025 에듀윌 소방설비기사 필기 전기분야 : 소방전기일반+소방전기시설의 구조 및 원리",
        "author": "손익희, 김윤수 저",
        "price": "31,500원",
        "url": "/Product/Goods/132545589"
    },
    {
        "imageURL": "https://image.yes24.com/goods/130171577/L",
        "title": "2025 초격차 소방설비기사·산업기사 필기 공통",
        "author": "황모아, 이지원, 오민정 저",
        "price": "35,550원",
        "url": "/Product/Goods/130171577"
    },
    {
        "imageURL": "https://image.yes24.com/goods/130171485/L",
        "title": "2025 초격차 소방설비기사·산업기사 필기 전기",
        "author": "황모아, 오민정 저",
        "price": "35,550원",
        "url": "/Product/Goods/130171485"
    },
    {
        "imageURL": "https://image.yes24.com/goods/130171444/L",
        "title": "2025 초격차 소방설비기사·산업기사 필기 기계",
        "author": "황모아, 이지원 저",
        "price": "35,550원",
        "url": "/Product/Goods/130171444"
    },
    {
        "imageURL": "https://image.yes24.com/goods/132849010/L",
        "title": "2025 초격차 소방설비기사 과년도 7개년 필기 기계",
        "author": "황모아, 이지원, 오민정 저",
        "price": "31,500원",
        "url": "/Product/Goods/132849010"
    },
    {
        "imageURL": "https://image.yes24.com/goods/132849029/L",
        "title": "2025 초격차 소방설비기사 과년도 7개년 필기 전기",
        "author": "황모아, 오민정, 이지원 저",
        "price": "33,300원",
        "url": "/Product/Goods/132849029"
    },
    {
        "imageURL": "https://image.yes24.com/goods/128850103/L",
        "title": "2024 화재안전기준",
        "author": "이기덕 편저",
        "price": "27,000원",
        "url": "/Product/Goods/128850103"
    },
    {
        "imageURL": "https://image.yes24.com/goods/128941942/L",
        "title": "쉽고 빠르게 합격하는 소방설비(산업)기사 전기분야 실기",
        "author": "이종오 편저",
        "price": "25,200원",
        "url": "/Product/Goods/128941942"
    },
    {
        "imageURL": "https://image.yes24.com/goods/124769075/L",
        "title": "2024 찐!합격 7개년 과년도 소방설비기사 실기 (전기4-7)",
        "author": "공하성 저",
        "price": "30,600원",
        "url": "/Product/Goods/124769075"
    },
    {
        "imageURL": "https://image.yes24.com/goods/124769117/L",
        "title": "2024 찐!합격 12개년 과년도 소방설비기사 실기 (전기5)",
        "author": "공하성 저",
        "price": "37,800원",
        "url": "/Product/Goods/124769117"
    },
    {
        "imageURL": "https://image.yes24.com/goods/124129792/L",
        "title": "2024 소방설비기사 실기 [전기분야]",
        "author": "표정은 저",
        "price": "33,300원",
        "url": "/Product/Goods/124129792"
    },
    {
        "imageURL": "https://image.yes24.com/goods/122499740/L",
        "title": "2024 에듀윌 소방설비기사 필기 기계분야 핵심이론+CBT적중문제+7개년 기출문제",
        "author": "김윤석, 이홍주 편저",
        "price": "30,600원",
        "url": "/Product/Goods/122499740"
    },
    {
        "imageURL": "https://image.yes24.com/goods/124006589/L",
        "title": "2024 소방설비기사 필기 (전기1)",
        "author": "공하성 저",
        "price": "41,400원",
        "url": "/Product/Goods/124006589"
    },
    {
        "imageURL": "https://image.yes24.com/goods/125300621/L",
        "title": "2024 에듀윌 소방설비기사 실기 전기분야 (핵심이론&빈출+12개년 기출)",
        "author": "우성천 편저",
        "price": "40,500원",
        "url": "/Product/Goods/125300621"
    },
    {
        "imageURL": "https://image.yes24.com/goods/124769140/L",
        "title": "2024 찐!합격 소방설비기사 실기 (전기 4)",
        "author": "공하성 저",
        "price": "43,200원",
        "url": "/Product/Goods/124769140"
    },
    {
        "imageURL": "https://image.yes24.com/goods/124487996/L",
        "title": "2024 에듀윌 소방설비기사 실기 기계분야",
        "author": "김윤석 편저",
        "price": "40,500원",
        "url": "/Product/Goods/124487996"
    },
    {
        "imageURL": "https://image.yes24.com/goods/124987520/L",
        "title": "2024 찐!합격 12개년 과년도 소방설비기사 실기 (기계5)",
        "author": "공하성 저",
        "price": "37,800원",
        "url": "/Product/Goods/124987520"
    },
    {
        "imageURL": "https://image.yes24.com/goods/124006659/L",
        "title": "2024 7개년 과년도 소방설비기사 필기 (전기1-7)",
        "author": "공하성 저",
        "price": "26,010원",
        "url": "/Product/Goods/124006659"
    },
    {
        "imageURL": "https://image.yes24.com/goods/124062723/L",
        "title": "2024 7개년 과년도 소방설비기사 필기 (기계1-7))",
        "author": "공하성 저",
        "price": "26,010원",
        "url": "/Product/Goods/124062723"
    },
    {
        "imageURL": "https://image.yes24.com/goods/124987589/L",
        "title": "2024 찐!합격 7개년 과년도 소방설비기사 실기 (기계4-7)",
        "author": "공하성 저",
        "price": "30,600원",
        "url": "/Product/Goods/124987589"
    },
    {
        "imageURL": "https://image.yes24.com/goods/122664871/L",
        "title": "2024 에듀윌 소방설비기사 필기 전기×기계(소방원론+소방관계법규)",
        "author": "김윤석, 이홍주 편저",
        "price": "34,200원",
        "url": "/Product/Goods/122664871"
    },
    {
        "imageURL": "https://image.yes24.com/goods/124539041/L",
        "title": "2024 초격차 소방설비기사·산업기사 실기전기",
        "author": "황모아, 오민정 저",
        "price": "33,300원",
        "url": "/Product/Goods/124539041"
    },
    {
        "imageURL": "https://image.yes24.com/goods/123255189/L",
        "title": "2024 소방설비기사 필기 전기분야",
        "author": "표정은, 최현준 저",
        "price": "29,700원",
        "url": "/Product/Goods/123255189"
    },
    {
        "imageURL": "https://image.yes24.com/goods/128939165/L",
        "title": "2025 이것이 진짜 해설이다 소방설비기사 실기(기계) 최근 11년 기출문제 재분류집",
        "author": "오철호 저",
        "price": "39,600원",
        "url": "/Product/Goods/128939165"
    },
    {
        "imageURL": "https://image.yes24.com/goods/132545589/L",
        "title": "2025 에듀윌 소방설비기사 필기 전기분야 : 소방전기일반+소방전기시설의 구조 및 원리",
        "author": "손익희, 김윤수 저",
        "price": "31,500원",
        "url": "/Product/Goods/132545589"
    },
    {
        "imageURL": "https://image.yes24.com/goods/130171577/L",
        "title": "2025 초격차 소방설비기사·산업기사 필기 공통",
        "author": "황모아, 이지원, 오민정 저",
        "price": "35,550원",
        "url": "/Product/Goods/130171577"
    },
    {
        "imageURL": "https://image.yes24.com/goods/130171485/L",
        "title": "2025 초격차 소방설비기사·산업기사 필기 전기",
        "author": "황모아, 오민정 저",
        "price": "35,550원",
        "url": "/Product/Goods/130171485"
    },
    {
        "imageURL": "https://image.yes24.com/goods/130171444/L",
        "title": "2025 초격차 소방설비기사·산업기사 필기 기계",
        "author": "황모아, 이지원 저",
        "price": "35,550원",
        "url": "/Product/Goods/130171444"
    },
    {
        "imageURL": "https://image.yes24.com/goods/132849010/L",
        "title": "2025 초격차 소방설비기사 과년도 7개년 필기 기계",
        "author": "황모아, 이지원, 오민정 저",
        "price": "31,500원",
        "url": "/Product/Goods/132849010"
    }
]